demo/__init__.py
demo/local_settings.py
demo/sass_variables.py
demo/settings.py
demo/urls.py
demo/views.py
demo/wsgi.py
psu_calendar/__init__.py
psu_calendar/admin.py
psu_calendar/apps.py
psu_calendar/models.py
psu_calendar/urls.py
psu_calendar/views.py
psu_calendar/classes/__init__.py
psu_calendar/classes/month.py
psu_calendar/migrations/__init__.py
psu_calendar/services/__init__.py
psu_calendar/services/calendar_service.py
psu_calendar/templates/psu_calendar/day.html
psu_calendar/templates/psu_calendar/month.html
psu_calendar/templates/psu_calendar/nav_header.html
psu_calendar/templates/psu_calendar/sample.html
psu_calendar/templates/psu_calendar/style.css
psu_calendar/templatetags/__init__.py
psu_calendar/templatetags/psu_calendar_taglib.py
psu_calendar/tests/__init__.py
psu_calendar/tests/test_applications.py
psu_calendar-0.0.3.dist-info/METADATA
psu_calendar-0.0.3.dist-info/WHEEL
psu_calendar-0.0.3.dist-info/top_level.txt
psu_calendar-0.0.3.dist-info/RECORD
